{
  "CommentUnion": ["CommentSuccess", "CommentUnionErrors"],
  "CreateEntriesUnion": ["CreateEntryErrors", "CreateEntrySuccess"],
  "CreateExperienceUnion": ["CreateExperienceErrors", "ExperienceSuccess"],
  "DeleteEntriesUnion": ["DeleteEntryErrors", "DeleteEntrySuccess"],
  "DeleteExperienceUnion": [
    "DeleteExperienceErrors",
    "DeleteExperienceSuccess"
  ],
  "DeleteExperiences": [
    "DeleteExperiencesAllFail",
    "DeleteExperiencesSomeSuccess"
  ],
  "GetEntriesUnion": ["GetEntriesErrors", "GetEntriesSuccess"],
  "GetExperienceCommentsUnion": [
    "GetExperienceCommentsErrors",
    "GetExperienceCommentsSuccess"
  ],
  "Login": ["LoginError", "UserSuccess"],
  "RegisterUser": ["RegisterUserErrors", "UserSuccess"],
  "UpdateDataObjectUnion": ["DataObjectErrors", "DataObjectSuccess"],
  "UpdateDefinition": ["DefinitionErrors", "DefinitionSuccess"],
  "UpdateExperienceOwnFieldsUnion": [
    "ExperienceOwnFieldsSuccess",
    "UpdateExperienceOwnFieldsErrors"
  ],
  "UpdateExperienceUnion": [
    "UpdateExperienceErrors",
    "UpdateExperienceSomeSuccess"
  ],
  "UpdateExperiencesUnion": [
    "UpdateExperiencesAllFail",
    "UpdateExperiencesSomeSuccess"
  ],
  "UpdateUser": ["UpdateUserErrors", "UserSuccess"],
  "UpdatedEntriesUnion": ["UpdateEntryErrors", "UpdateEntrySomeSuccess"]
}
